{
  "project_info": {
    "project_number": "525082069132",
    "firebase_url": "https://etrener-42f94.firebaseio.com",
    "project_id": "etrener-42f94",
    "storage_bucket": "etrener-42f94.appspot.com"
  },
  "client": [
    {
      "client_info": {
        "mobilesdk_app_id": "1:525082069132:android:c71d620f23410fb6",
        "android_client_info": {
          "package_name": "com.example.luke.trener"
        }
      },
      "oauth_client": [
        {
          "client_id": "525082069132-p9q7e2tgfno5iv84chpqoo9uq5lal0pp.apps.googleusercontent.com",
          "client_type": 3
        }
      ],
      "api_key": [
        {
          "current_key": "AIzaSyAjP_rb_Mp0HPMkwsueXFCWg22_NUy8pu4"
        }
      ],
      "services": {
        "analytics_service": {
          "status": 1
        },
        "appinvite_service": {
          "status": 1,
          "other_platform_oauth_client": []
        },
        "ads_service": {
          "status": 2
        }
      }
    }
  ],
  "configuration_version": "1"
}